nicepdf/__init__.py
nicepdf/nicepdf_cmd.py
nicepdf/pdftool.py
nicepdf/version.py
nicepdf/webserver.py
nicepdf_examples/example_booklet_2.pdf
nicepdf-0.1.0.dist-info/METADATA
nicepdf-0.1.0.dist-info/WHEEL
nicepdf-0.1.0.dist-info/entry_points.txt
nicepdf-0.1.0.dist-info/licenses/LICENSE
nicepdf-0.1.0.dist-info/RECORD
