Metadata-Version: 2.1
Name: nicepdf
Version: 0.1.0
Summary: nicegui based PDF manipulation tool - e.g. booklet conversion
Project-URL: Home, https://github.com/WolfgangFahl/nicepdf
Project-URL: Documentation, https://wiki.bitplan.com/index.php/nicepdf
Project-URL: Source, https://github.com/WolfgangFahl/nicepdf
Author-email: Wolfgang Fahl <wf@bitplan.com>
Maintainer-email: Wolfgang Fahl <wf@bitplan.com>
License-Expression: Apache-2.0
License-File: LICENSE
Keywords: nicegui,pdf
Classifier: Development Status :: 4 - Beta
Classifier: Environment :: Console
Classifier: Intended Audience :: Developers
Classifier: Intended Audience :: Education
Classifier: License :: OSI Approved :: Apache Software License
Classifier: Operating System :: OS Independent
Classifier: Programming Language :: Python :: 3 :: Only
Classifier: Programming Language :: Python :: 3.8
Classifier: Programming Language :: Python :: 3.9
Classifier: Programming Language :: Python :: 3.10
Classifier: Topic :: Software Development :: Libraries :: Python Modules
Requires-Python: >=3.8
Requires-Dist: ngwidgets>=0.3.0
Requires-Dist: nicegui
Requires-Dist: pypdf>=3.17.4
Requires-Dist: reportlab>=3.5.67
Requires-Dist: tqdm>=4.60.0
Provides-Extra: test
Requires-Dist: green; extra == 'test'
